sas_airflow_provider/__init__.py
sas_airflow_provider/example_dags/__init__.py
sas_airflow_provider/example_dags/example_sas_jobexecution.py
sas_airflow_provider/example_dags/example_sas_studio.py
sas_airflow_provider/example_dags/example_studio_advanced.py
sas_airflow_provider/example_dags/example_templating.py
sas_airflow_provider/hooks/__init__.py
sas_airflow_provider/hooks/sas.py
sas_airflow_provider/operators/__init__.py
sas_airflow_provider/operators/sas_create_session.py
sas_airflow_provider/operators/sas_delete_session.py
sas_airflow_provider/operators/sas_jobexecution.py
sas_airflow_provider/operators/sas_studio.py
sas_airflow_provider/operators/sas_studioflow.py
sas_airflow_provider/util/__init__.py
sas_airflow_provider/util/util.py
sas_airflow_provider-0.0.22.dist-info/LICENSE
sas_airflow_provider-0.0.22.dist-info/METADATA
sas_airflow_provider-0.0.22.dist-info/WHEEL
sas_airflow_provider-0.0.22.dist-info/entry_points.txt
sas_airflow_provider-0.0.22.dist-info/top_level.txt
sas_airflow_provider-0.0.22.dist-info/RECORD
