Metadata-Version: 2.1
Name: sas-airflow-provider
Version: 0.0.22
Summary: Enables execution of Studio Flows and Jobs from Airflow
Home-page: https://github.com/sassoftware/sas-airflow-provider
Author: SAS
Author-email: andrew.shakinovsky@sas.com
Project-URL: Bug Tracker, https://github.com/sassoftware
Classifier: Programming Language :: Python :: 3
Classifier: License :: OSI Approved :: Apache Software License
Classifier: Operating System :: OS Independent
Requires-Python: >=3.7
License-File: LICENSE
